threatkb.py
threatkb-1.0.0a2.dist-info/METADATA
threatkb-1.0.0a2.dist-info/RECORD
threatkb-1.0.0a2.dist-info/WHEEL
threatkb-1.0.0a2.dist-info/entry_points.txt
threatkb-1.0.0a2.dist-info/top_level.txt
