Metadata-Version: 2.1
Name: threatkb
Version: 1.0.0a2
Summary: API and command-line tool for InQuest ThreatKB
Home-page: https://github.com/InQuest/python-threatkb
Author: InQuest Labs
Author-email: labs@inquest.net
License: BSD
Platform: UNKNOWN
Classifier: Intended Audience :: Developers
Classifier: Intended Audience :: Information Technology
Classifier: Intended Audience :: System Administrators
Classifier: License :: OSI Approved :: BSD License
Classifier: Operating System :: OS Independent
Classifier: Programming Language :: Python
Classifier: Topic :: Security
Classifier: Topic :: Software Development :: Libraries
Classifier: Topic :: Internet
Requires-Dist: requests
